graphai/__init__.py
graphai/callback.py
graphai/graph.py
graphai/py.typed
graphai/utils.py
graphai/nodes/__init__.py
graphai/nodes/base.py
graphai_lib-0.0.9.dist-info/METADATA
graphai_lib-0.0.9.dist-info/WHEEL
graphai_lib-0.0.9.dist-info/top_level.txt
graphai_lib-0.0.9.dist-info/RECORD
